qianlu_svr_plugin/__init__.py
qianlu_svr_plugin/server.py
qianlu_svr_plugin/test.py
qianlu_svr_plugin-0.0.15.dist-info/METADATA
qianlu_svr_plugin-0.0.15.dist-info/WHEEL
qianlu_svr_plugin-0.0.15.dist-info/top_level.txt
qianlu_svr_plugin-0.0.15.dist-info/RECORD
