Metadata-Version: 2.1
Name: qianlu-svr-plugin
Version: 0.0.15
Summary: this is service base plugin by websocket
Author: bxwx123
Classifier: Programming Language :: Python :: 3
Classifier: License :: OSI Approved :: MIT License
Classifier: Operating System :: OS Independent
Requires-Python: >=3.6
